llm_parametrizer/__init__.py
llm_parametrizer/llm_parametrizer.py
llm_parametrizer/open_AI_models.py
llm_parametrizer-0.1.2.dist-info/METADATA
llm_parametrizer-0.1.2.dist-info/WHEEL
llm_parametrizer-0.1.2.dist-info/top_level.txt
llm_parametrizer-0.1.2.dist-info/RECORD
