Metadata-Version: 2.1
Name: llm-parametrizer
Version: 0.1.2
Summary: A library to parametrize multiple API calls for LLMs
Home-page: https://github.com/arjuna-dev/llm_parametrizer
Author: Alejandro Camus
License: UNKNOWN
Platform: UNKNOWN
Requires-Dist: openai
Requires-Dist: python-dotenv
